LICENSE
README.md
setup.py
sqlcoder/__init__.py
sqlcoder/cli.py
sqlcoder/integration_routes.py
sqlcoder/query_routes.py
sqlcoder/serve.py
sqlcoder.egg-info/PKG-INFO
sqlcoder.egg-info/SOURCES.txt
sqlcoder.egg-info/dependency_links.txt
sqlcoder.egg-info/entry_points.txt
sqlcoder.egg-info/requires.txt
sqlcoder.egg-info/top_level.txt
sqlcoder/static/404.html
sqlcoder/static/extract-metadata.html
sqlcoder/static/favicon.ico
sqlcoder/static/index.html
sqlcoder/static/instruct-model.html
sqlcoder/static/next.svg
sqlcoder/static/query-data.html
sqlcoder/static/vercel.svg
sqlcoder/static/_next/static/PhIFrR5mo2t2wIFmxfdiU/_buildManifest.js
sqlcoder/static/_next/static/PhIFrR5mo2t2wIFmxfdiU/_ssgManifest.js
sqlcoder/static/_next/static/chunks/0c428ae2.7f5ab17ef2110d84.js
sqlcoder/static/_next/static/chunks/238-21e16f207d48d221.js
sqlcoder/static/_next/static/chunks/283.503b46c22e64c702.js
sqlcoder/static/_next/static/chunks/9b8d1757.9dd2c712a441d5f8.js
sqlcoder/static/_next/static/chunks/ea88be26.e203a40320569dfc.js
sqlcoder/static/_next/static/chunks/faae6fda.7ebb95670d232bb0.js
sqlcoder/static/_next/static/chunks/framework-02223fe42ab9321b.js
sqlcoder/static/_next/static/chunks/main-d30d248d262e39c4.js
sqlcoder/static/_next/static/chunks/polyfills-c67a75d1b6f99dc8.js
sqlcoder/static/_next/static/chunks/webpack-1657be5a4830bbb9.js
sqlcoder/static/_next/static/chunks/pages/_app-db0976def6406e5e.js
sqlcoder/static/_next/static/chunks/pages/_error-ee42a9921d95ff81.js
sqlcoder/static/_next/static/chunks/pages/extract-metadata-2dc614052128d5d3.js
sqlcoder/static/_next/static/chunks/pages/index-a1b2fa2d87d27d8d.js
sqlcoder/static/_next/static/chunks/pages/instruct-model-634351430965962f.js
sqlcoder/static/_next/static/chunks/pages/query-data-0be55b0a48827890.js
sqlcoder/static/_next/static/css/321c398b2a784143.css