Metadata-Version: 2.1
Name: sqlcoder
Version: 0.2.0
Summary: SQLCoder is a large language model for converting text questions in SQL queries.
Home-page: https://github.com/defog-ai/sqlcoder
Author: Defog, Inc
Author-email: founders@defog.ai
License: Apache-2
Platform: UNKNOWN
Provides-Extra: llama-cpp
Provides-Extra: transformers
License-File: LICENSE
